LatexLunwenXiezuoJiaocheng/README.md
LatexLunwenXiezuoJiaocheng/__init__.py
LatexLunwenXiezuoJiaocheng/__main__.py
LatexLunwenXiezuoJiaocheng/file.epub
LatexLunwenXiezuoJiaocheng/index.html
LatexLunwenXiezuoJiaocheng/css/__init__.py
LatexLunwenXiezuoJiaocheng/css/annotations.css
LatexLunwenXiezuoJiaocheng/css/main.css
LatexLunwenXiezuoJiaocheng/css/normalize.css
LatexLunwenXiezuoJiaocheng/css/popup.css
LatexLunwenXiezuoJiaocheng/font/__init__.py
LatexLunwenXiezuoJiaocheng/font/fontello.eot
LatexLunwenXiezuoJiaocheng/font/fontello.svg
LatexLunwenXiezuoJiaocheng/font/fontello.ttf
LatexLunwenXiezuoJiaocheng/font/fontello.woff
LatexLunwenXiezuoJiaocheng/img/__init__.py
LatexLunwenXiezuoJiaocheng/img/annotator-glyph-sprite.png
LatexLunwenXiezuoJiaocheng/img/annotator-icon-sprite.png
LatexLunwenXiezuoJiaocheng/img/apple-touch-icon.png
LatexLunwenXiezuoJiaocheng/img/cancelfullscreen.png
LatexLunwenXiezuoJiaocheng/img/close.png
LatexLunwenXiezuoJiaocheng/img/fullscreen.png
LatexLunwenXiezuoJiaocheng/img/loader.gif
LatexLunwenXiezuoJiaocheng/img/menu-icon.png
LatexLunwenXiezuoJiaocheng/img/save.png
LatexLunwenXiezuoJiaocheng/img/saved.png
LatexLunwenXiezuoJiaocheng/img/settings-s.png
LatexLunwenXiezuoJiaocheng/img/settings.png
LatexLunwenXiezuoJiaocheng/img/star.png
LatexLunwenXiezuoJiaocheng/js/__init__.py
LatexLunwenXiezuoJiaocheng/js/epub.js
LatexLunwenXiezuoJiaocheng/js/epub.min.js
LatexLunwenXiezuoJiaocheng/js/epub.min.map
LatexLunwenXiezuoJiaocheng/js/hooks.min.js
LatexLunwenXiezuoJiaocheng/js/hooks.min.map
LatexLunwenXiezuoJiaocheng/js/reader.js
LatexLunwenXiezuoJiaocheng/js/reader.js.map
LatexLunwenXiezuoJiaocheng/js/reader.min.js
LatexLunwenXiezuoJiaocheng/js/reader.min.map
LatexLunwenXiezuoJiaocheng/js/hooks/__init__.py
LatexLunwenXiezuoJiaocheng/js/hooks/extensions/__init__.py
LatexLunwenXiezuoJiaocheng/js/hooks/extensions/highlight.js
LatexLunwenXiezuoJiaocheng/js/libs/__init__.py
LatexLunwenXiezuoJiaocheng/js/libs/jquery.min.js
latex_lunwen_xiezuo_jiaocheng-2024.3.6.0.dist-info/METADATA
latex_lunwen_xiezuo_jiaocheng-2024.3.6.0.dist-info/WHEEL
latex_lunwen_xiezuo_jiaocheng-2024.3.6.0.dist-info/entry_points.txt
latex_lunwen_xiezuo_jiaocheng-2024.3.6.0.dist-info/top_level.txt
latex_lunwen_xiezuo_jiaocheng-2024.3.6.0.dist-info/RECORD
